{"cameraMode":{"drawMode":0,"name":"Shaded","section":"Shading Mode"},"sceneLighting":true,"audioPlay":false,"sceneViewState":{"m_AlwaysRefresh":false,"showFog":true,"showSkybox":true,"showFlares":true,"showImageEffects":true,"showParticleSystems":true,"showVisualEffectGraphs":true,"m_FxEnabled":true},"in2DMode":false,"pivot":{"x":-8.10135555267334,"y":0.5003814697265625,"z":-11.54478645324707},"rotation":{"x":0.13381539285182954,"y":-0.856644332408905,"z":0.2765900492668152,"w":0.4144461750984192},"size":62.44388198852539,"orthographic":false}